nqueens_solver/__init__.py
nqueens_solver/solver.py
nqueens_solver-0.2.0.dist-info/licenses/LICENSE
tests/__init__.py
tests/test_solver.py
nqueens_solver-0.2.0.dist-info/METADATA
nqueens_solver-0.2.0.dist-info/WHEEL
nqueens_solver-0.2.0.dist-info/top_level.txt
nqueens_solver-0.2.0.dist-info/RECORD
